infercode/__init__.py
infercode/__main__.py
infercode/client/__init__.py
infercode/client/base_client.py
infercode/client/infercode_client.py
infercode/client/infercode_trainer.py
infercode/configs/__init__.py
infercode/configs/__version__.py
infercode/configs/default_config.ini
infercode/data_utils/__init__.py
infercode/data_utils/ast_parser.py
infercode/data_utils/ast_util.py
infercode/data_utils/data_loader.py
infercode/data_utils/dataset_processor.py
infercode/data_utils/language_util.py
infercode/data_utils/subtree_util.py
infercode/data_utils/subtree_vocab_extractor.py
infercode/data_utils/tensor_util.py
infercode/data_utils/threaded_iterator.py
infercode/data_utils/token_vocab_extractor.py
infercode/data_utils/vocabulary.py
infercode/network/__init__.py
infercode/network/infercode_network.py
infercode/script/__init__.py
infercode/script/build_vocab_from_file.py
infercode/script/extract_subtree_vocab.py
infercode/script/extract_token_vocab.py
infercode/script/filter_subtrees.py
infercode/script/process_data.py
infercode/script/remove_comments.py
infercode/script/remove_non_english.py
infercode/sentencepiece_vocab/__init__.py
infercode/sentencepiece_vocab/node_types/node_types_all.model
infercode/sentencepiece_vocab/node_types/node_types_all.vocab
infercode/sentencepiece_vocab/node_types/node_types_bash.model
infercode/sentencepiece_vocab/node_types/node_types_bash.vocab
infercode/sentencepiece_vocab/node_types/node_types_c-sharp.model
infercode/sentencepiece_vocab/node_types/node_types_c-sharp.vocab
infercode/sentencepiece_vocab/node_types/node_types_c.model
infercode/sentencepiece_vocab/node_types/node_types_c.vocab
infercode/sentencepiece_vocab/node_types/node_types_cpp.model
infercode/sentencepiece_vocab/node_types/node_types_cpp.vocab
infercode/sentencepiece_vocab/node_types/node_types_css.model
infercode/sentencepiece_vocab/node_types/node_types_css.vocab
infercode/sentencepiece_vocab/node_types/node_types_elm.model
infercode-0.0.34.dist-info/LICENSE-APACHE
infercode-0.0.34.dist-info/METADATA
infercode-0.0.34.dist-info/WHEEL
infercode-0.0.34.dist-info/top_level.txt
infercode-0.0.34.dist-info/RECORD
