Metadata-Version: 2.2
Name: infercode
Version: 0.0.34
Home-page: https://github.com/trusted-programming/infercode/
Author-email: "Nghi D. Q. Bui" <bdqnghi@gmail.com>, Yijun Yu <y.yu@open.ac.uk>, Lingxiao Jiang <lxjiang@smu.edu.sg>
License:                                  Apache License
Classifier: Development Status :: 3 - Alpha
Classifier: License :: OSI Approved :: MIT License
Classifier: Operating System :: OS Independent
Classifier: Programming Language :: Python :: 3
Classifier: Intended Audience :: Developers
License-File: LICENSE-APACHE
Requires-Dist: bidict>=0.21.2
Requires-Dist: coloredlogs>=15.0.1
Requires-Dist: dpu_utils>=0.2.19
Requires-Dist: keras_radam>=0.15.0
Requires-Dist: numpy>=1.19.4
Requires-Dist: protobuf>=3.14.0
Requires-Dist: scikit_learn>=0.24.0
Requires-Dist: scipy>=1.5.2
Requires-Dist: sentencepiece>=0.1.95
Requires-Dist: tensorflow==2.5.0
Requires-Dist: tqdm>=4.55.1
Requires-Dist: tree_sitter==0.19.0
Requires-Dist: tree_sitter_parsers>=0.0.7
Requires-Dist: utils>=1.0.1
Dynamic: home-page
